{"bltfcadff56954eba39":{"title":"Home","url":"/","seo":{"meta_keywords":"","meta_description":"","canonical_url":"","no_index":false,"no_follow":false},"page_elements":[{"banner":{"headline":"Welcome to adventure","_metadata":{"uid":"csbe54bd6ff967ebc9"},"sub_header":"","banner_image":{"uid":"bltcdf2c2adb596f6e1","created_at":"2025-02-05T15:03:27.461Z","updated_at":"2025-02-05T15:03:27.461Z","created_by":"cs6570221eb30a96cc","updated_by":"cs6570221eb30a96cc","content_type":"image/jpeg","file_size":"314755","tags":[],"filename":"Wrangell-StEllias-Banner.jpg","url":"https://images.contentstack.io/v3/assets/blt007136d3bb9fec54/bltcdf2c2adb596f6e1/67a37dbfa8d855c287b70afa/Wrangell-StEllias-Banner.jpg","ACL":[],"is_dir":false,"parent_uid":"blte71d6361baa98708","_version":1,"title":"Wrangell-StEllias-Banner.jpg","publish_details":[{"environment":"blt54a77ceb5fbf5e6d","locale":"en-us","time":"2025-02-05T16:32:16.205Z","user":"cs6570221eb30a96cc","version":1}]}}},{"cta_row":{"cta":[{"uid":"blt81542dd47a876395","_content_type_uid":"cta"},{"uid":"bltceffaf4d08c473eb","_content_type_uid":"cta"},{"uid":"blt2fa9aee83bcf66d4","_content_type_uid":"cta"}],"_metadata":{"uid":"cs705d988fadbb6ec4"}}}],"tags":[],"locale":"en-us","uid":"bltfcadff56954eba39","ACL":{},"_version":10,"_in_progress":false,"publish_details":[{"environment":"blt54a77ceb5fbf5e6d","locale":"en-us","time":"2025-04-02T16:51:41.750Z","user":"cs6570221eb30a96cc","version":10}]},"blt93985bc55b89fbfc":{"title":"About us","url":"/about-us","seo":{"meta_keywords":"","meta_description":"","canonical_url":"","no_index":false,"no_follow":false},"page_elements":[{"banner":{"headline":"Roots of Adventure","sub_header":"","banner_image":{"uid":"blt77f4d23f499409fe","created_at":"2025-02-05T15:15:56.327Z","updated_at":"2025-02-05T15:15:56.327Z","created_by":"cs6570221eb30a96cc","updated_by":"cs6570221eb30a96cc","content_type":"image/jpeg","file_size":"86290","tags":[],"filename":"GrandTeton-Aurao-Banner.jpg","url":"https://images.contentstack.io/v3/assets/blt007136d3bb9fec54/blt77f4d23f499409fe/67a380ac8028ff56d6ea0a4c/GrandTeton-Aurao-Banner.jpg","ACL":[],"is_dir":false,"parent_uid":"blte71d6361baa98708","_version":1,"title":"GrandTeton-Aurao-Banner.jpg","publish_details":[{"environment":"blt54a77ceb5fbf5e6d","locale":"en-us","time":"2025-02-05T16:32:16.192Z","user":"cs6570221eb30a96cc","version":1}]},"_metadata":{"uid":"csfa67a93d14e4baae"}}}],"tags":[],"locale":"en-us","uid":"blt93985bc55b89fbfc","ACL":{},"_version":1,"_in_progress":false,"publish_details":[{"environment":"blt54a77ceb5fbf5e6d","locale":"en-us","time":"2025-02-14T14:38:18.718Z","user":"cs6570221eb30a96cc","version":1}]},"blt5bfda91c49712aa5":{"title":"From The Trail","url":"/fromthetrail","seo":{"meta_keywords":"","meta_description":"","canonical_url":"","no_index":false,"no_follow":false},"page_elements":[{"banner":{"headline":"From The Trail","_metadata":{"uid":"csf2db15abc84f440e"},"sub_header":"","banner_image":{"uid":"blt32a5bcb951163d2b","created_at":"2025-02-05T16:12:48.339Z","updated_at":"2025-02-05T16:12:48.339Z","created_by":"cs6570221eb30a96cc","updated_by":"cs6570221eb30a96cc","content_type":"image/jpeg","file_size":"47430","tags":[],"filename":"JOTR_NPSBradSutton_960w.jpg","url":"https://images.contentstack.io/v3/assets/blt007136d3bb9fec54/blt32a5bcb951163d2b/67a38e0005be66773434f280/JOTR_NPSBradSutton_960w.jpg","ACL":[],"is_dir":false,"parent_uid":"blte71d6361baa98708","_version":1,"title":"JOTR_NPSBradSutton_960w.jpg","publish_details":[{"environment":"blt54a77ceb5fbf5e6d","locale":"en-us","time":"2025-02-05T16:32:16.125Z","user":"cs6570221eb30a96cc","version":1}]}}},{"filter_listing":{"listing":[{"uid":"bltf602a6cbc9a9c7f2","_content_type_uid":"listing_display"}],"_metadata":{"uid":"cs7f40ec87319db132"}}},{"external_action_link":{"display_label":"this is the display","target":{"title":"this is the target","href":"https://www.google.com"},"_metadata":{"uid":"csb101ce6c8d49ca9b"}}}],"tags":[],"locale":"en-us","uid":"blt5bfda91c49712aa5","ACL":{},"_version":3,"_in_progress":false,"publish_details":[{"environment":"blt54a77ceb5fbf5e6d","locale":"en-us","time":"2025-02-07T14:31:43.272Z","user":"cs6570221eb30a96cc","version":3}]},"blt02b95c21d79891f1":{"title":"News","url":"/news","seo":{"meta_keywords":"","meta_description":"","canonical_url":"","no_index":false,"no_follow":false},"page_elements":[{"banner":{"headline":"The Happenings","_metadata":{"uid":"cse84586033796248f"},"sub_header":"","banner_image":{"uid":"blt4c3bc5615b7e794c","created_at":"2025-02-05T15:56:53.641Z","updated_at":"2025-02-05T15:56:53.641Z","created_by":"cs6570221eb30a96cc","updated_by":"cs6570221eb30a96cc","content_type":"image/jpeg","file_size":"599897","tags":[],"filename":"zunden_in_wild.jpg","url":"https://images.contentstack.io/v3/assets/blt007136d3bb9fec54/blt4c3bc5615b7e794c/67a38a45122899a5f73b1753/zunden_in_wild.jpg","ACL":[],"is_dir":false,"parent_uid":"blte71d6361baa98708","_version":1,"title":"zunden_in_wild.jpg","publish_details":[{"environment":"blt54a77ceb5fbf5e6d","locale":"en-us","time":"2025-02-05T16:32:16.140Z","user":"cs6570221eb30a96cc","version":1}]}}},{"filter_listing":{"listing":[{"uid":"bltadb8fc28c7530c4a","_content_type_uid":"listing_display"}],"_metadata":{"uid":"cs92eff6302d4b9942"}}}],"tags":[],"locale":"en-us","uid":"blt02b95c21d79891f1","ACL":{},"_version":2,"_in_progress":false,"publish_details":[{"environment":"blt54a77ceb5fbf5e6d","locale":"en-us","time":"2025-02-05T16:32:15.686Z","user":"cs6570221eb30a96cc","version":2}]},"bltedee19f813aa732a":{"title":"Products","url":"/products","seo":{"meta_keywords":"","meta_description":"","canonical_url":"","no_index":false,"no_follow":false},"page_elements":[{"banner":{"headline":"Gear That Will Make It To The End","_metadata":{"uid":"cs5bfa9132f05ca08b"},"sub_header":"","banner_image":{"uid":"blt6c7a5cd210fd914d","created_at":"2025-02-05T15:54:30.849Z","updated_at":"2025-02-05T15:54:49.775Z","created_by":"cs6570221eb30a96cc","updated_by":"cs6570221eb30a96cc","content_type":"image/webp","file_size":"175622","tags":[],"filename":"firemaple-stove-banner.webp","url":"https://images.contentstack.io/v3/assets/blt007136d3bb9fec54/blt6c7a5cd210fd914d/67a389b6ecc9d72ca1414881/firemaple-stove-banner.webp","ACL":[],"is_dir":false,"parent_uid":"blte71d6361baa98708","_version":2,"title":"firemaple-stove-banner.webp","publish_details":[{"environment":"blt54a77ceb5fbf5e6d","locale":"en-us","time":"2025-02-05T16:32:16.154Z","user":"cs6570221eb30a96cc","version":2}]}}},{"products":{"headline":"Some of Our Favorites","sub_header":"","products_for_display":[{"uid":"bltdd4c6d0a84c5a725","_content_type_uid":"product"},{"uid":"blt8d74cf0a538e7dcc","_content_type_uid":"product"}],"action_link_label":"","action_link":[],"_metadata":{"uid":"cs44c01755cfa1ac23"}}}],"tags":[],"locale":"en-us","uid":"bltedee19f813aa732a","ACL":{},"_version":2,"_in_progress":false,"publish_details":[{"environment":"blt54a77ceb5fbf5e6d","locale":"en-us","time":"2025-02-05T16:32:15.715Z","user":"cs6570221eb30a96cc","version":2}]},"bltbb7cdcd3a09e9b95":{"title":"Events","url":"/events","seo":{"meta_keywords":"","meta_description":"","canonical_url":"","no_index":false,"no_follow":false},"page_elements":[{"banner":{"headline":"Adventures to Be Found Around Every Corner","sub_header":"","banner_image":{"uid":"blt77f4d23f499409fe","created_at":"2025-02-05T15:15:56.327Z","updated_at":"2025-02-05T15:15:56.327Z","created_by":"cs6570221eb30a96cc","updated_by":"cs6570221eb30a96cc","content_type":"image/jpeg","file_size":"86290","tags":[],"filename":"GrandTeton-Aurao-Banner.jpg","url":"https://images.contentstack.io/v3/assets/blt007136d3bb9fec54/blt77f4d23f499409fe/67a380ac8028ff56d6ea0a4c/GrandTeton-Aurao-Banner.jpg","ACL":[],"is_dir":false,"parent_uid":"blte71d6361baa98708","_version":1,"title":"GrandTeton-Aurao-Banner.jpg","publish_details":[{"environment":"blt54a77ceb5fbf5e6d","locale":"en-us","time":"2025-02-05T16:32:16.192Z","user":"cs6570221eb30a96cc","version":1}]},"_metadata":{"uid":"csf787dcfb2cd3594d"}}},{"filter_listing":{"listing":[{"uid":"blt503c7a8a8952deda","_content_type_uid":"listing_display"}],"_metadata":{"uid":"csf0ab9b19529406ef"}}}],"tags":[],"locale":"en-us","uid":"bltbb7cdcd3a09e9b95","ACL":{},"_version":1,"_in_progress":false,"publish_details":[{"environment":"blt54a77ceb5fbf5e6d","locale":"en-us","time":"2025-02-05T16:32:15.758Z","user":"cs6570221eb30a96cc","version":1}]}}